astar_utils/__init__.py
astar_utils/badges.py
astar_utils/loggers.py
astar_utils/nested_mapping.py
astar_utils/spectral_types.py
astar_utils/unique_list.py
astar_utils-0.4.0.dist-info/LICENSE
astar_utils-0.4.0.dist-info/METADATA
astar_utils-0.4.0.dist-info/WHEEL
astar_utils-0.4.0.dist-info/RECORD
