Metadata-Version: 2.3
Name: astar-utils
Version: 0.4.0
Summary: Contains commonly-used utilities for AstarVienna's projects.
License: GPL-3.0-or-later
Author: Fabian Haberhauer
Author-email: fabian.haberhauer@univie.ac.at
Maintainer: Fabian Haberhauer
Maintainer-email: fabian.haberhauer@univie.ac.at
Requires-Python: >=3.10,<3.14
Classifier: Intended Audience :: Science/Research
Classifier: License :: OSI Approved :: GNU General Public License v3 or later (GPLv3+)
Classifier: Operating System :: OS Independent
Classifier: Programming Language :: Python :: 3
Classifier: Programming Language :: Python :: 3.10
Classifier: Programming Language :: Python :: 3.11
Classifier: Programming Language :: Python :: 3.12
Classifier: Programming Language :: Python :: 3.13
Classifier: Topic :: Scientific/Engineering :: Astronomy
Classifier: Topic :: Utilities
Requires-Dist: colorama (>=0.4.6,<1.0)
Requires-Dist: more-itertools (>=10.2.0,<11.0.0)
Requires-Dist: pyyaml (>=6.0.2,<7.0.0)
Project-URL: Changelog, https://github.com/AstarVienna/astar-utils/releases
Project-URL: Repository, https://github.com/AstarVienna/astar-utils
